yk8s/__init__.py
yk8s-0.0.0.dist-info/METADATA
yk8s-0.0.0.dist-info/WHEEL
yk8s-0.0.0.dist-info/top_level.txt
yk8s-0.0.0.dist-info/RECORD
