Metadata-Version: 2.1
Name: yk8s
Version: 0.0.0
Summary: Coming soon
Author-email: Cloud&Heat <info@cloudandheat.com>
